horse-0.2.4.dist-info/metadata.json
horse-0.2.4.dist-info/DESCRIPTION.rst
horse-0.2.4.dist-info/METADATA
horse-0.2.4.dist-info/RECORD
horse-0.2.4.dist-info/top_level.txt
horse-0.2.4.dist-info/WHEEL
horse/config.py
horse/slack.py
horse/__init__.py
horse/database.py
horse/jockey.py
horse/models.py
