Metadata-Version: 2.0
Name: horse
Version: 0.2.4
Summary: A chat bot framework for Slack
Home-page: https://github.com/grieve/horse
Author: Ryan Grieve
Author-email: me@ryangrieve.com
License: MIT
Keywords: chatbot slack chat bot communication
Platform: UNKNOWN
Classifier: Development Status :: 3 - Alpha
Classifier: Intended Audience :: Developers
Classifier: Topic :: Communications :: Chat
Classifier: License :: OSI Approved :: MIT License
Classifier: Programming Language :: Python :: 2
Classifier: Programming Language :: Python :: 2.6
Classifier: Programming Language :: Python :: 2.7
Classifier: Programming Language :: Python :: 3
Classifier: Programming Language :: Python :: 3.2
Classifier: Programming Language :: Python :: 3.3
Classifier: Programming Language :: Python :: 3.4
Requires-Dist: websocket-client
Requires-Dist: requests
Requires-Dist: sqlobject
Requires-Dist: flask
Provides-Extra: dev
Provides-Extra: test
